{
	"name": "Layout 1",
	"layers": [
		{
			"name": "Layer 0",
			"overriden": 0,
			"subLayers": [],
			"instances": [
				{
					"type": "background",
					"properties": {
						"initially-visible": true,
						"origin": "top-left",
						"wrap-horizontal": "repeat",
						"wrap-vertical": "repeat",
						"image-offset-x": 0,
						"image-offset-y": 0,
						"image-scale-x": 1,
						"image-scale-y": 1,
						"image-angle": 0,
						"enable-tile-randomization": false,
						"x-random": 1,
						"y-random": 1,
						"angle-random": 1,
						"blend-margin-x": 0.1,
						"blend-margin-y": 0.1
					},
					"uid": 2,
					"instanceVariables": {},
					"behaviors": {},
					"world": {
						"x": -0.1626674704712272,
						"y": -1,
						"width": 855.1626674704712,
						"height": 483,
						"originX": 0,
						"originY": 0,
						"color": [
							1,
							1,
							1,
							1
						],
						"angle": 0,
						"zElevation": 0
					}
				},
				{
					"type": "lantai",
					"properties": {
						"initially-visible": true,
						"tile-width": 32,
						"tile-height": 32,
						"tile-x-offset": 0,
						"tile-y-offset": 0,
						"tile-x-spacing": 0,
						"tile-y-spacing": 0,
						"tile-x-drawing-offset": 0,
						"tile-y-drawing-offset": 0,
						"drawing-mode": "top-to-right"
					},
					"uid": 3,
					"instanceVariables": {},
					"behaviors": {},
					"ownData": {
						"tilemapData": {
							"width": 53,
							"height": 30,
							"max-width": 53,
							"max-height": 30,
							"data": "244x0,1,11,21,31,41,51,61,71,81,91,20x0,2,12,22,32,42,52,62,72,82,92,20x0,3,13,23,33,43,53,63,73,83,93,20x0,4,14,24,34,44,54,64,74,84,94,20x0,5,15,25,35,45,55,65,75,85,95,20x0,6,16,26,36,46,56,66,76,86,96,20x0,7,17,27,37,47,57,67,77,87,97,20x0,8,18,28,38,48,58,68,78,88,98,20x0,9,19,29,39,49,59,69,79,89,99,20x0,10,20,30,40,50,60,70,80,90,100,1066x0"
						},
						"tile-width": 32,
						"tile-height": 32,
						"tile-x-offset": 0,
						"tile-y-offset": 0,
						"tile-x-spacing": 0,
						"tile-y-spacing": 0
					},
					"world": {
						"x": 0,
						"y": 0,
						"width": 1708,
						"height": 960,
						"originX": 0,
						"originY": 0,
						"color": [
							1,
							1,
							1,
							1
						],
						"zElevation": 0
					}
				},
				{
					"type": "Dinding",
					"properties": {
						"initially-visible": true,
						"tile-width": 32,
						"tile-height": 32,
						"tile-x-offset": 0,
						"tile-y-offset": 0,
						"tile-x-spacing": 0,
						"tile-y-spacing": 0,
						"tile-x-drawing-offset": 0,
						"tile-y-drawing-offset": 0,
						"drawing-mode": "top-to-right"
					},
					"uid": 4,
					"instanceVariables": {},
					"behaviors": {},
					"ownData": {
						"tilemapData": {
							"width": 53,
							"height": 30,
							"max-width": 53,
							"max-height": 30,
							"data": "243x0,21,29x0,22,29x0,23,30x0,34,29x0,35,29x0,36,29x0,37,28x0,28,29x0,29,29x0,30,1076x0"
						},
						"tile-width": 32,
						"tile-height": 32,
						"tile-x-offset": 0,
						"tile-y-offset": 0,
						"tile-x-spacing": 0,
						"tile-y-spacing": 0
					},
					"world": {
						"x": 0,
						"y": 0,
						"width": 1708,
						"height": 960,
						"originX": 0,
						"originY": 0,
						"color": [
							1,
							1,
							1,
							1
						],
						"zElevation": 0
					}
				},
				{
					"type": "DindingSolid",
					"properties": {
						"initially-visible": true,
						"tile-width": 32,
						"tile-height": 32,
						"tile-x-offset": 0,
						"tile-y-offset": 0,
						"tile-x-spacing": 0,
						"tile-y-spacing": 0,
						"tile-x-drawing-offset": 0,
						"tile-y-drawing-offset": 0,
						"drawing-mode": "top-to-right"
					},
					"uid": 5,
					"instanceVariables": {},
					"behaviors": {
						"Solid": {
							"properties": {
								"enabled": true,
								"tags": ""
							}
						}
					},
					"ownData": {
						"tilemapData": {
							"width": 53,
							"height": 30,
							"max-width": 53,
							"max-height": 30,
							"data": "241x0,1,11,28x0,2,12,28x0,3,13,29x0,14,24,28x0,15,25,28x0,16,26,28x0,17,27,27x0,8,18,28x0,9,19,28x0,10,20,1077x0"
						},
						"tile-width": 32,
						"tile-height": 32,
						"tile-x-offset": 0,
						"tile-y-offset": 0,
						"tile-x-spacing": 0,
						"tile-y-spacing": 0
					},
					"world": {
						"x": 0,
						"y": 0,
						"width": 1708,
						"height": 960,
						"originX": 0,
						"originY": 0,
						"color": [
							1,
							1,
							1,
							1
						],
						"zElevation": 0
					}
				},
				{
					"type": "Player",
					"properties": {
						"initially-visible": true,
						"initial-animation": "Atas",
						"initial-frame": 0,
						"enable-collisions": true,
						"live-preview": false
					},
					"uid": 6,
					"instanceVariables": {},
					"behaviors": {
						"8Direction": {
							"properties": {
								"max-speed": 100,
								"acceleration": 600,
								"deceleration": 500,
								"directions": "dir-8",
								"set-angle": "no",
								"allow-sliding": false,
								"default-controls": true,
								"enabled": true
							}
						}
					},
					"world": {
						"x": 552.2884625725652,
						"y": 331.5688461776301,
						"width": 32,
						"height": 64,
						"originX": 0.5,
						"originY": 0.5,
						"color": [
							1,
							1,
							1,
							1
						],
						"angle": 0,
						"zElevation": 0
					}
				},
				{
					"type": "papanTulis",
					"properties": {
						"initially-visible": true,
						"initial-animation": "Animation 1",
						"initial-frame": 0,
						"enable-collisions": true,
						"live-preview": false
					},
					"uid": 8,
					"instanceVariables": {},
					"behaviors": {},
					"world": {
						"x": 415.54029099069817,
						"y": 114.97246491620862,
						"width": 96,
						"height": 61,
						"originX": 0.5,
						"originY": 0.5,
						"color": [
							1,
							1,
							1,
							1
						],
						"angle": 0,
						"zElevation": 0
					}
				},
				{
					"type": "PinggiranSolid",
					"properties": {
						"initially-visible": true,
						"tile-width": 32,
						"tile-height": 32,
						"tile-x-offset": 0,
						"tile-y-offset": 0,
						"tile-x-spacing": 0,
						"tile-y-spacing": 0,
						"tile-x-drawing-offset": 0,
						"tile-y-drawing-offset": 0,
						"drawing-mode": "top-to-right"
					},
					"uid": 10,
					"instanceVariables": {},
					"behaviors": {
						"Solid": {
							"properties": {
								"enabled": true,
								"tags": ""
							}
						}
					},
					"ownData": {
						"tilemapData": {
							"width": 53,
							"height": 30,
							"max-width": 53,
							"max-height": 30,
							"data": "210x0,1,13,12x25,37,15x0,2,13x0,38,15x0,3,13x0,39,15x0,4,13x0,40,15x0,5,17,12x0,41,15x0,6,18,12x0,42,15x0,7,19,12x0,43,15x0,8,20,12x0,44,15x0,9,13x0,45,15x0,10,13x0,46,15x0,11,13x0,47,15x0,12,24,8x36,0,3x36,48,1035x0"
						},
						"tile-width": 32,
						"tile-height": 32,
						"tile-x-offset": 0,
						"tile-y-offset": 0,
						"tile-x-spacing": 0,
						"tile-y-spacing": 0
					},
					"world": {
						"x": 0,
						"y": 0,
						"width": 1708,
						"height": 960,
						"originX": 0,
						"originY": 0,
						"color": [
							1,
							1,
							1,
							1
						],
						"zElevation": 0
					}
				},
				{
					"type": "rak",
					"properties": {
						"initially-visible": true,
						"initial-animation": "Animation 1",
						"initial-frame": 0,
						"enable-collisions": true,
						"live-preview": false
					},
					"uid": 11,
					"instanceVariables": {},
					"behaviors": {
						"Solid": {
							"properties": {
								"enabled": true,
								"tags": ""
							}
						}
					},
					"world": {
						"x": 272.0243771354612,
						"y": 269.18260252509424,
						"width": 32,
						"height": 154,
						"originX": 0.5,
						"originY": 0.5,
						"color": [
							1,
							1,
							1,
							1
						],
						"angle": 0,
						"zElevation": 0
					}
				},
				{
					"type": "PintuDestroy",
					"properties": {
						"initially-visible": true,
						"tile-width": 32,
						"tile-height": 32,
						"tile-x-offset": 0,
						"tile-y-offset": 0,
						"tile-x-spacing": 0,
						"tile-y-spacing": 0,
						"tile-x-drawing-offset": 0,
						"tile-y-drawing-offset": 0,
						"drawing-mode": "top-to-right"
					},
					"uid": 12,
					"instanceVariables": {},
					"behaviors": {
						"Solid": {
							"properties": {
								"enabled": true,
								"tags": ""
							}
						}
					},
					"ownData": {
						"tilemapData": {
							"width": 53,
							"height": 30,
							"max-width": 53,
							"max-height": 30,
							"data": "550x0,36,1039x0"
						},
						"tile-width": 32,
						"tile-height": 32,
						"tile-x-offset": 0,
						"tile-y-offset": 0,
						"tile-x-spacing": 0,
						"tile-y-spacing": 0
					},
					"world": {
						"x": 0,
						"y": 0,
						"width": 1708,
						"height": 960,
						"originX": 0,
						"originY": 0,
						"color": [
							1,
							1,
							1,
							1
						],
						"zElevation": 0
					}
				},
				{
					"type": "boxIjoTua",
					"properties": {
						"initially-visible": true,
						"initial-animation": "Default",
						"initial-frame": 0,
						"enable-collisions": true,
						"live-preview": false
					},
					"uid": 13,
					"instanceVariables": {},
					"behaviors": {
						"Solid": {
							"properties": {
								"enabled": true,
								"tags": ""
							}
						}
					},
					"world": {
						"x": 346.06338358056666,
						"y": 304.4744810624571,
						"width": 32,
						"height": 47,
						"originX": 0.5,
						"originY": 0.5,
						"color": [
							1,
							1,
							1,
							1
						],
						"angle": 0,
						"zElevation": 0
					}
				},
				{
					"type": "boxBiruMuda",
					"properties": {
						"initially-visible": true,
						"initial-animation": "Default",
						"initial-frame": 0,
						"enable-collisions": true,
						"live-preview": false
					},
					"uid": 14,
					"instanceVariables": {},
					"behaviors": {
						"Solid": {
							"properties": {
								"enabled": true,
								"tags": ""
							}
						}
					},
					"world": {
						"x": 398.26767446975026,
						"y": 371.2786480664566,
						"width": 32,
						"height": 47,
						"originX": 0.5,
						"originY": 0.5,
						"color": [
							1,
							1,
							1,
							1
						],
						"angle": 0,
						"zElevation": 0
					}
				},
				{
					"type": "boxOren",
					"properties": {
						"initially-visible": true,
						"initial-animation": "Default",
						"initial-frame": 0,
						"enable-collisions": true,
						"live-preview": false
					},
					"uid": 15,
					"instanceVariables": {},
					"behaviors": {
						"Solid": {
							"properties": {
								"enabled": true,
								"tags": ""
							}
						}
					},
					"world": {
						"x": 529.2590042828854,
						"y": 210.67274643238684,
						"width": 32,
						"height": 47,
						"originX": 0.5,
						"originY": 0.5,
						"color": [
							1,
							1,
							1,
							1
						],
						"angle": 0,
						"zElevation": 0
					}
				},
				{
					"type": "boxIjoMuda",
					"properties": {
						"initially-visible": true,
						"initial-animation": "Default",
						"initial-frame": 0,
						"enable-collisions": true,
						"live-preview": false
					},
					"uid": 16,
					"instanceVariables": {},
					"behaviors": {
						"Solid": {
							"properties": {
								"enabled": true,
								"tags": ""
							}
						}
					},
					"world": {
						"x": 398.9567971978304,
						"y": 236.2924221711393,
						"width": 32,
						"height": 47,
						"originX": 0.5,
						"originY": 0.5,
						"color": [
							1,
							1,
							1,
							1
						],
						"angle": 0,
						"zElevation": 0
					}
				},
				{
					"type": "boxBiruTua",
					"properties": {
						"initially-visible": true,
						"initial-animation": "Default",
						"initial-frame": 0,
						"enable-collisions": true,
						"live-preview": false
					},
					"uid": 17,
					"instanceVariables": {},
					"behaviors": {
						"Solid": {
							"properties": {
								"enabled": true,
								"tags": ""
							}
						}
					},
					"world": {
						"x": 489.86567305467685,
						"y": 351.99479656114534,
						"width": 32,
						"height": 47,
						"originX": 0.5,
						"originY": 0.5,
						"color": [
							1,
							1,
							1,
							1
						],
						"angle": 0,
						"zElevation": 0
					}
				},
				{
					"type": "triggerOren",
					"properties": {
						"initially-visible": true,
						"tile-width": 32,
						"tile-height": 32,
						"tile-x-offset": 0,
						"tile-y-offset": 0,
						"tile-x-spacing": 0,
						"tile-y-spacing": 0,
						"tile-x-drawing-offset": 0,
						"tile-y-drawing-offset": 0,
						"drawing-mode": "top-to-right"
					},
					"uid": 18,
					"instanceVariables": {},
					"behaviors": {},
					"ownData": {
						"tilemapData": {
							"width": 53,
							"height": 30,
							"max-width": 53,
							"max-height": 30,
							"data": "523x0,1,1066x0"
						},
						"tile-width": 32,
						"tile-height": 32,
						"tile-x-offset": 0,
						"tile-y-offset": 0,
						"tile-x-spacing": 0,
						"tile-y-spacing": 0
					},
					"world": {
						"x": 0,
						"y": 0,
						"width": 1708,
						"height": 960,
						"originX": 0,
						"originY": 0,
						"color": [
							1,
							1,
							1,
							0
						],
						"zElevation": 0
					}
				},
				{
					"type": "triggerIjoMuda",
					"properties": {
						"initially-visible": true,
						"tile-width": 32,
						"tile-height": 32,
						"tile-x-offset": 0,
						"tile-y-offset": 0,
						"tile-x-spacing": 0,
						"tile-y-spacing": 0,
						"tile-x-drawing-offset": 0,
						"tile-y-drawing-offset": 0,
						"drawing-mode": "top-to-right"
					},
					"uid": 19,
					"instanceVariables": {},
					"behaviors": {},
					"ownData": {
						"tilemapData": {
							"width": 53,
							"height": 30,
							"max-width": 53,
							"max-height": 30,
							"data": "398x0,1,1191x0"
						},
						"tile-width": 32,
						"tile-height": 32,
						"tile-x-offset": 0,
						"tile-y-offset": 0,
						"tile-x-spacing": 0,
						"tile-y-spacing": 0
					},
					"world": {
						"x": 0,
						"y": 0,
						"width": 1708,
						"height": 960,
						"originX": 0,
						"originY": 0,
						"color": [
							1,
							1,
							1,
							0
						],
						"zElevation": 0
					}
				},
				{
					"type": "triggerIjoTua",
					"properties": {
						"initially-visible": true,
						"tile-width": 32,
						"tile-height": 32,
						"tile-x-offset": 0,
						"tile-y-offset": 0,
						"tile-x-spacing": 0,
						"tile-y-spacing": 0,
						"tile-x-drawing-offset": 0,
						"tile-y-drawing-offset": 0,
						"drawing-mode": "top-to-right"
					},
					"uid": 20,
					"instanceVariables": {},
					"behaviors": {},
					"ownData": {
						"tilemapData": {
							"width": 53,
							"height": 30,
							"max-width": 53,
							"max-height": 30,
							"data": "493x0,1,1096x0"
						},
						"tile-width": 32,
						"tile-height": 32,
						"tile-x-offset": 0,
						"tile-y-offset": 0,
						"tile-x-spacing": 0,
						"tile-y-spacing": 0
					},
					"world": {
						"x": 0,
						"y": 0,
						"width": 1708,
						"height": 960,
						"originX": 0,
						"originY": 0,
						"color": [
							1,
							1,
							1,
							0
						],
						"zElevation": 0
					}
				},
				{
					"type": "triggerBiruTua",
					"properties": {
						"initially-visible": true,
						"tile-width": 32,
						"tile-height": 32,
						"tile-x-offset": 0,
						"tile-y-offset": 0,
						"tile-x-spacing": 0,
						"tile-y-spacing": 0,
						"tile-x-drawing-offset": 0,
						"tile-y-drawing-offset": 0,
						"drawing-mode": "top-to-right"
					},
					"uid": 21,
					"instanceVariables": {},
					"behaviors": {},
					"ownData": {
						"tilemapData": {
							"width": 53,
							"height": 30,
							"max-width": 53,
							"max-height": 30,
							"data": "244x0,1,1345x0"
						},
						"tile-width": 32,
						"tile-height": 32,
						"tile-x-offset": 0,
						"tile-y-offset": 0,
						"tile-x-spacing": 0,
						"tile-y-spacing": 0
					},
					"world": {
						"x": 0,
						"y": 0,
						"width": 1708,
						"height": 960,
						"originX": 0,
						"originY": 0,
						"color": [
							1,
							1,
							1,
							0
						],
						"zElevation": 0
					}
				},
				{
					"type": "triggerBiruMuda",
					"properties": {
						"initially-visible": true,
						"tile-width": 32,
						"tile-height": 32,
						"tile-x-offset": 0,
						"tile-y-offset": 0,
						"tile-x-spacing": 0,
						"tile-y-spacing": 0,
						"tile-x-drawing-offset": 0,
						"tile-y-drawing-offset": 0,
						"drawing-mode": "top-to-right"
					},
					"uid": 22,
					"instanceVariables": {},
					"behaviors": {},
					"ownData": {
						"tilemapData": {
							"width": 53,
							"height": 30,
							"max-width": 53,
							"max-height": 30,
							"data": "274x0,1,1315x0"
						},
						"tile-width": 32,
						"tile-height": 32,
						"tile-x-offset": 0,
						"tile-y-offset": 0,
						"tile-x-spacing": 0,
						"tile-y-spacing": 0
					},
					"world": {
						"x": 0,
						"y": 0,
						"width": 1708,
						"height": 960,
						"originX": 0,
						"originY": 0,
						"color": [
							1,
							1,
							1,
							0
						],
						"zElevation": 0
					}
				},
				{
					"type": "misi",
					"properties": {
						"initially-visible": true,
						"initial-animation": "clue 1",
						"initial-frame": 0,
						"enable-collisions": true,
						"live-preview": false
					},
					"uid": 24,
					"instanceVariables": {},
					"behaviors": {},
					"world": {
						"x": 126.20118347884548,
						"y": 73.7767433655977,
						"width": 206.21453513157294,
						"height": 95.90218139853873,
						"originX": 0.5,
						"originY": 0.5,
						"color": [
							1,
							1,
							1,
							1
						],
						"angle": 0,
						"zElevation": 0
					}
				},
				{
					"type": "PATOKANPINTUKELUAR",
					"properties": {
						"initially-visible": true,
						"tile-width": 32,
						"tile-height": 32,
						"tile-x-offset": 0,
						"tile-y-offset": 0,
						"tile-x-spacing": 0,
						"tile-y-spacing": 0,
						"tile-x-drawing-offset": 0,
						"tile-y-drawing-offset": 0,
						"drawing-mode": "top-to-right"
					},
					"uid": 25,
					"instanceVariables": {},
					"behaviors": {},
					"ownData": {
						"tilemapData": {
							"width": 53,
							"height": 30,
							"max-width": 53,
							"max-height": 30,
							"data": "520x0,1,1069x0"
						},
						"tile-width": 32,
						"tile-height": 32,
						"tile-x-offset": 0,
						"tile-y-offset": 0,
						"tile-x-spacing": 0,
						"tile-y-spacing": 0
					},
					"world": {
						"x": 0,
						"y": 0,
						"width": 1708,
						"height": 960,
						"originX": 0,
						"originY": 0,
						"color": [
							1,
							1,
							1,
							0
						],
						"zElevation": 0
					}
				}
			],
			"sid": 521688380082641,
			"effectTypes": [],
			"isInitiallyVisible": true,
			"isInitiallyInteractive": true,
			"color": [
				1,
				1,
				1,
				1
			],
			"backgroundColor": [
				0.3686274509803922,
				0.3686274509803922,
				0.3686274509803922,
				1
			],
			"isTransparent": false,
			"parallaxX": 1,
			"parallaxY": 1,
			"scaleRate": 1,
			"forceOwnTexture": false,
			"renderingMode": "3d",
			"drawOrder": "z-order",
			"useRenderCells": false,
			"blendMode": "normal",
			"zElevation": 0,
			"global": false
		},
		{
			"name": "Pop Up",
			"overriden": 0,
			"subLayers": [],
			"instances": [
				{
					"type": "PopUpPapanTulis",
					"properties": {
						"initially-visible": true,
						"initial-animation": "Animation 1",
						"initial-frame": 0,
						"enable-collisions": true,
						"live-preview": false
					},
					"uid": 9,
					"instanceVariables": {},
					"behaviors": {},
					"world": {
						"x": 417.21316676588583,
						"y": 238.75660560346068,
						"width": 401.8929778188807,
						"height": 228.5131552580278,
						"originX": 0.5,
						"originY": 0.5,
						"color": [
							1,
							1,
							1,
							1
						],
						"angle": 0,
						"zElevation": 0
					}
				},
				{
					"type": "KAMUBERHASIL",
					"properties": {
						"initially-visible": true,
						"initial-animation": "Default",
						"initial-frame": 0,
						"enable-collisions": true,
						"live-preview": false
					},
					"uid": 23,
					"instanceVariables": {},
					"behaviors": {},
					"world": {
						"x": 426.26882596316347,
						"y": 239.27251462224405,
						"width": 851.6842749659581,
						"height": 479.0724048212305,
						"originX": 0.5,
						"originY": 0.5,
						"color": [
							1,
							1,
							1,
							1
						],
						"angle": 0,
						"zElevation": 0
					}
				}
			],
			"sid": 148693651656406,
			"effectTypes": [],
			"isInitiallyVisible": true,
			"isInitiallyInteractive": true,
			"color": [
				1,
				1,
				1,
				1
			],
			"backgroundColor": [
				0.3686274509803922,
				0.3686274509803922,
				0.3686274509803922,
				1
			],
			"isTransparent": true,
			"parallaxX": 1,
			"parallaxY": 1,
			"scaleRate": 1,
			"forceOwnTexture": false,
			"renderingMode": "3d",
			"drawOrder": "z-order",
			"useRenderCells": false,
			"blendMode": "normal",
			"zElevation": 0,
			"global": false
		}
	],
	"sid": 128510655191377,
	"nonworld-instances": [],
	"effectTypes": [],
	"width": 1708,
	"height": 960,
	"unboundedScrolling": false,
	"vpX": 0.5,
	"vpY": 0.5,
	"projection": "perspective",
	"eventSheet": "Event sheet 1"
}